syvmo/__init__.py
syvmo/cdist_fixed.py
syvmo/construction.py
syvmo/feature_array.py
syvmo/oracle_segmentation.py
syvmo/plot_fo.py
syvmo/generation/SyVMO.py
syvmo/generation/VMO.py
syvmo/generation/__init__.py
syvmo/oracles/__init__.py
syvmo/oracles/factor_oracle.py
syvmo/oracles/fo.py
syvmo/oracles/utils.py
syvmo/oracles/vmo.py
syvmo-0.0.1.dist-info/LICENSE
syvmo-0.0.1.dist-info/METADATA
syvmo-0.0.1.dist-info/WHEEL
syvmo-0.0.1.dist-info/top_level.txt
syvmo-0.0.1.dist-info/RECORD
